langdechat/__init__.py
langdechat/langeval.py
langdechat-0.1.1.dist-info/LICENSE
langdechat-0.1.1.dist-info/METADATA
langdechat-0.1.1.dist-info/WHEEL
langdechat-0.1.1.dist-info/top_level.txt
langdechat-0.1.1.dist-info/RECORD
